{  
   "status":"ok",
   "source":"espn",
   "sortBy":"top",
   "articles":[  
      {  
         "author":"Dana O'NeilESPN Senior Writer",
         "title":"The Final Four of never, never, almost never and North Carolina",
         "description":"This is South Carolina's first trip to the Final Four. Same for Gonzaga. Oregon has been here before, in 1939. Then there's North Carolina, for a 20th time. No, this isn't your normal Final Four.",
         "url":"http://espn.go.com/mens-college-basketball/story/_/id/19011719/south-carolina-oregon-gonzaga-north-carolina-make-eclectic-final-four",
         "urlToImage":"http://a4.espncdn.com/combiner/i?img=%2Fphoto%2F2017%2F0326%2Fr194093_1296x729_16%2D9.jpg",
         "publishedAt":"2017-03-27T02:29:25Z"
      },
      {  
         "author":null,
         "title":"The moment that brought each team to the Final Four",
         "description":"It takes talented players, good coaching and a little luck to win four straight games in the NCAA tournament. But for each Final Four team, there was a singular moment where it all clicked.",
         "url":"http://espn.go.com/mens-college-basketball/story/_/id/19008696/the-moment-made-2016-17-ncaa-tournament-final-four-team",
         "urlToImage":"http://a4.espncdn.com/combiner/i?img=%2Fphoto%2F2017%2F0326%2Fr193972_2_1296x729_16%2D9.jpg",
         "publishedAt":"2017-03-27T02:50:42Z"
      },
      {  
         "author":"Myron MedcalfESPN Staff Writer",
         "title":"A miracle in Memphis: North Carolina back in the Final Four",
         "description":"UNC is back in the Final Four, where it'll answer questions about the miracle shot in Memphis, not just the one that ended the Heels' 2015-16 season.",
         "url":"http://espn.go.com/blog/collegebasketballnation/post/_/id/119190/a-miracle-in-memphis-north-carolina-back-in-the-final-four",
         "urlToImage":"http://a.espncdn.com/combiner/i?img=%2Fphoto%2F2017%2F0326%2Fr194102_1296x729_16%2D9.jpg",
         "publishedAt":"2017-03-27T02:22:30Z"
      },
      {  
         "author":"Calvin WatkinsESPN Staff Writer",
         "title":"Rockets use offense to roll past Thunder",
         "description":"The offensive display by the Rockets on Sunday afternoon was another indication of how difficult this team will be to defeat when the playoffs begin.",
         "url":"http://espn.go.com/blog/houston-rockets/post/_/id/3854/rockets-use-offense-to-roll-past-thunder",
         "urlToImage":"http://a2.espncdn.com/combiner/i?img=%2Fphoto%2F2017%2F0326%2Fr194078_1296x729_16%2D9.jpg",
         "publishedAt":"2017-03-27T00:53:45Z"
      },
      {  
         "author":"Chris ForsbergESPN Staff Writer",
         "title":"Shots aren't falling but Marcus Smart still impacts winning for Celtics",
         "description":"Even though Marcus Smart may not lead the Celtics in scoring, his propensity for making big plays during key moments has kept him on the floor.",
         "url":"http://espn.go.com/blog/boston/celtics/post/_/id/4725662/shots-arent-falling-but-marcus-smart-still-impacts-winning-for-celtics",
         "urlToImage":"http://a2.espncdn.com/combiner/i?img=%2Fphoto%2F2017%2F0326%2Fr194118_1296x729_16%2D9.jpg",
         "publishedAt":"2017-03-27T03:21:12Z"
      },
      {  
         "author":"Ethan Sherwood StraussESPN Staff Writer",
         "title":"Klay Thompson's hot streak allows Warriors to distance themselves from Grizzlies",
         "description":"Klay Thompson's shooting allowed Warriors to keep up with Grizzlies until Memphis ran out of gas in the fourth quarter.",
         "url":"http://espn.go.com/blog/golden-state-warriors/post/_/id/4142/klay-thompsons-hot-streak-allow-warriors-to-distance-themselves-from-grizzlies",
         "urlToImage":"http://a3.espncdn.com/combiner/i?img=%2Fphoto%2F2017%2F0326%2Fr194114_1296x729_16%2D9.jpg",
         "publishedAt":"2017-03-27T03:55:14Z"
      },
      {  
         "author":"Baxter HolmesESPN Staff Writer",
         "title":"Kobe pulls back curtain on post-NBA storytelling venture",
         "description":"His life after basketball in full swing, Kobe Bryant details his latest project: \"Canvas City,\" the second of six features Bryant agreed to direct, write and create for ESPN.",
         "url":"http://espn.go.com/nba/story/_/id/19008734/kobe-bryant-pulls-back-curtain-post-nba-storytelling-venture",
         "urlToImage":"http://a2.espncdn.com/combiner/i?img=%2Fphoto%2F2016%2F0824%2Fr118408_1296x729_16%2D9.jpg",
         "publishedAt":"2017-03-27T01:12:26Z"
      },
      {  
         "author":"Dana O'NeilESPN Senior Writer",
         "title":"South Carolina's local approach pays off in trip to the Final Four",
         "description":"PJ Dozier and Sindarius Thornwell, both of whom decided to stay in South Carolina, led the Gamecocks past Florida and into the program's first Final Four appearance.",
         "url":"http://espn.go.com/mens-college-basketball/story/_/id/19011170/south-carolina-gamecocks-head-final-four-florida-gators-led-two-stars-stayed-home",
         "urlToImage":"http://a3.espncdn.com/combiner/i?img=%2Fphoto%2F2017%2F0326%2Fr193994_1296x729_16%2D9.jpg",
         "publishedAt":"2017-03-27T03:26:58Z"
      },
      {  
         "author":"Mechelle VoepelespnW.com",
         "title":"William's 41 points lead Bulldogs to first Final Four",
         "description":"Morgan William hit 6 of 8 3-point attempts and scored a career-high 41 points to drive No. 2 seed Mississippi State to its first Final Four. The Bulldogs beat top-seeded Baylor in overtime 94-85.",
         "url":"http://espn.go.com/womens-college-basketball/story/_/id/19011208/women-ncaa-tournament-morgan-william-scores-41-points-lead-mississippi-state-first-final-four",
         "urlToImage":"http://a.espncdn.com/combiner/i?img=%2Fphoto%2F2017%2F0326%2Fr194085_1296x729_16%2D9.jpg",
         "publishedAt":"2017-03-27T02:35:17Z"
      },
      {  
         "author":"Graham HaysespnW.com",
         "title":"McPhee, Stanford topple 1-seed Notre Dame to reach Final Four",
         "description":"In a career-defining performance, junior Brittany McPhee scored 27 points -- including 19 in the second half -- to help Stanford overcome a 16-point deficit and reach its 13th Final Four.",
         "url":"http://espn.go.com/womens-college-basketball/story/_/id/19009370/women-ncaa-tournament-brittany-mcphee-stanford-cardinal-topple-1-seed-notre-dame-fighting-irish-reach-final-four",
         "urlToImage":"http://a.espncdn.com/combiner/i?img=%2Fphoto%2F2017%2F0326%2Fr193987_1296x729_16%2D9.jpg",
         "publishedAt":"2017-03-27T00:13:27Z"
      }
   ]
}